epregressions/__init__.py
epregressions/build_files_to_run.py
epregressions/energyplus.py
epregressions/ep.png
epregressions/ep_platform.py
epregressions/epw_map.py
epregressions/runner.py
epregressions/runtests.py
epregressions/structures.py
epregressions/tk_window.py
epregressions/builds/__init__.py
epregressions/builds/base.py
epregressions/builds/install.py
epregressions/builds/makefile.py
epregressions/builds/visualstudio.py
epregressions/diffs/__init__.py
epregressions/diffs/ci_compare_script.py
epregressions/diffs/math_diff.config
epregressions/diffs/math_diff.py
epregressions/diffs/mycsv.py
epregressions/diffs/table_diff.py
epregressions/diffs/thresh_dict.py
epregressions/tests/__init__.py
epregressions/tests/test_build_files_to_run.py
epregressions/tests/test_energyplus.py
epregressions/tests/test_epw_map.py
epregressions/tests/test_platform.py
epregressions/tests/test_runtests.py
epregressions/tests/test_structures.py
epregressions/tests/builds/__init__.py
epregressions/tests/builds/test_base.py
epregressions/tests/builds/test_install.py
epregressions/tests/builds/test_makefile.py
epregressions/tests/builds/test_visualstudio.py
epregressions/tests/diffs/__init__.py
epregressions/tests/diffs/test_ci_compare_script.py
epregressions/tests/diffs/test_math_diff.py
epregressions/tests/diffs/test_mycsv.py
epregressions/tests/diffs/test_table_diff.py
epregressions/tests/diffs/test_thresh_dict.py
epregressions/tests/diffs/csv_resources/test_math_diff.config
epregressions/tests/diffs/tbl_resources/test_table_diff.config
EnergyPlusRegressionTool-1.9.6.dist-info/LICENSE
EnergyPlusRegressionTool-1.9.6.dist-info/METADATA
EnergyPlusRegressionTool-1.9.6.dist-info/WHEEL
EnergyPlusRegressionTool-1.9.6.dist-info/entry_points.txt
EnergyPlusRegressionTool-1.9.6.dist-info/top_level.txt
EnergyPlusRegressionTool-1.9.6.dist-info/RECORD
