Metadata-Version: 2.1
Name: EnergyPlusRegressionTool
Version: 1.9.6
Summary: A Python 3 library for evaluating regressions between EnergyPlus builds.
Home-page: https://github.com/NREL/EnergyPlusRegressionTool
Author: Edwin Lee
Author-email: 
License: UNKNOWN
Keywords: energyplus
Platform: UNKNOWN
Requires-Python: >=3.5
Requires-Dist: PyPubSub (==4.0.3)
Requires-Dist: beautifulsoup4 (==4.9.3)
